data_visualization/__init__.py
data_visualization/register.py
data_visualization/frontend/dist/index.html
data_visualization/frontend/dist/vite.svg
data_visualization/frontend/dist/assets/index-8b489cec.js
data_visualization/frontend/dist/assets/index-d081bea5.css
test_data_visualization-0.0.2.dist-info/LICENSE
test_data_visualization-0.0.2.dist-info/METADATA
test_data_visualization-0.0.2.dist-info/WHEEL
test_data_visualization-0.0.2.dist-info/top_level.txt
test_data_visualization-0.0.2.dist-info/RECORD
