Metadata-Version: 2.1
Name: test-data-visualization
Version: 0.0.2
Summary: Show data in charts
Home-page: UNKNOWN
Author: Bluepinapple
Author-email: viveksthul@bluepinapple.com
License: UNKNOWN
Platform: UNKNOWN
Requires-Python: >=3.9.6
Requires-Dist: streamlit (>=1.20.0)
